Metadata-Version: 2.1
Name: spinneration
Version: 0.0.0
Summary: A module for displaying progress messages and timers with spinners in the command line.
Home-page: https://github.com/Shahaf-F-S/spinneroo
Author: Shahaf Frank-Shapir
Author-email: shahaffrs@gmail.com
License: MIT
Classifier: Intended Audience :: Developers
Classifier: License :: OSI Approved :: MIT License
Classifier: Programming Language :: Python
Classifier: Programming Language :: Python :: 3
Classifier: Programming Language :: Python :: 3.8
Classifier: Programming Language :: Python :: 3.9
Classifier: Programming Language :: Python :: 3.10
Classifier: Programming Language :: Python :: 3.11
Classifier: Operating System :: OS Independent
Requires-Dist: pyrepresent
Requires-Dist: spinners
Requires-Dist: looperator
Provides-Extra: dev
Requires-Dist: pdoc3; extra == "dev"
Requires-Dist: twine; extra == "dev"
